humax/__init__.py
humax/__version__.py
humax/cli.py
humax/humax.py
humax-0.1.0.dist-info/METADATA
humax-0.1.0.dist-info/WHEEL
humax-0.1.0.dist-info/entry_points.txt
humax-0.1.0.dist-info/top_level.txt
humax-0.1.0.dist-info/RECORD
